trialpack/__init__.py
trialpack/tp.py
trialpack-1.0.1.dist-info/METADATA
trialpack-1.0.1.dist-info/WHEEL
trialpack-1.0.1.dist-info/top_level.txt
trialpack-1.0.1.dist-info/RECORD
