Metadata-Version: 2.1
Name: trialpack
Version: 1.0.1
Summary: A custom 'this' module with programming principles and poem
Home-page: https://github.com/NINJAGAMING107/trialpack
Author: Sidharth (NINJA)
Author-email: sidharthsnair357@gmail.com
Classifier: Programming Language :: Python :: 3
Classifier: License :: OSI Approved :: MIT License
Classifier: Operating System :: OS Independent
Requires-Python: >=3.6
